ethereum_rpc/__init__.py
ethereum_rpc/_keccak.py
ethereum_rpc/_rpc.py
ethereum_rpc/_serialization.py
ethereum_rpc/_typed_wrappers.py
ethereum_rpc/py.typed
ethereum_rpc-0.1.1.dist-info/WHEEL
ethereum_rpc-0.1.1.dist-info/METADATA
ethereum_rpc-0.1.1.dist-info/licenses/LICENSE.md
ethereum_rpc-0.1.1.dist-info/RECORD
