Metadata-Version: 2.1
Name: ethereum-rpc
Version: 0.1.1
Summary: Ethereum RPC types
Author-email: Bogdan Opanchuk <bogdan@opanchuk.net>
Requires-Python: >=3.10
Classifier: Development Status :: 4 - Beta
Classifier: License :: OSI Approved :: MIT License
Classifier: Operating System :: OS Independent
Classifier: Programming Language :: Python :: 3
Requires-Dist: compages>=0.3
Requires-Dist: pycryptodome>=3
Provides-Extra: docs
Requires-Dist: sphinx>=4; extra == "docs"
Requires-Dist: furo; extra == "docs"
Requires-Dist: setuptools-scm; extra == "docs"
Provides-Extra: lint
Requires-Dist: mypy>=1.4; extra == "lint"
Requires-Dist: ruff>=0.2; extra == "lint"
Provides-Extra: tests
Requires-Dist: pytest>=6; extra == "tests"
Requires-Dist: pytest-cov; extra == "tests"
Project-URL: homepage, https://github.com/fjarri-eth/ethereum-rpc
